<annotation>
	<folder>validation</folder>
	<filename>36.jpg</filename>
	<path>/home/fdlopes/Área de Trabalho/object-detection/images/validation/36.jpg</path>
	<source>
		<database>Unknown</database>
	</source>
	<size>
		<width>720</width>
		<height>960</height>
		<depth>3</depth>
	</size>
	<segmented>0</segmented>
	<object>
		<name>banana</name>
		<pose>Unspecified</pose>
		<truncated>0</truncated>
		<difficult>0</difficult>
		<bndbox>
			<xmin>297</xmin>
			<ymin>406</ymin>
			<xmax>428</xmax>
			<ymax>484</ymax>
		</bndbox>
	</object>
</annotation>
