<annotation>
	<folder>orange</folder>
	<filename>orange_99.jpg</filename>
	<path>/home/fdlopes/Área de Trabalho/dataset/orange/orange_99.jpg</path>
	<source>
		<database>Unknown</database>
	</source>
	<size>
		<width>799</width>
		<height>571</height>
		<depth>3</depth>
	</size>
	<segmented>0</segmented>
	<object>
		<name>orange</name>
		<pose>Unspecified</pose>
		<truncated>0</truncated>
		<difficult>0</difficult>
		<bndbox>
			<xmin>308</xmin>
			<ymin>367</ymin>
			<xmax>476</xmax>
			<ymax>513</ymax>
		</bndbox>
	</object>
	<object>
		<name>orange</name>
		<pose>Unspecified</pose>
		<truncated>0</truncated>
		<difficult>0</difficult>
		<bndbox>
			<xmin>288</xmin>
			<ymin>210</ymin>
			<xmax>462</xmax>
			<ymax>368</ymax>
		</bndbox>
	</object>
</annotation>
